appPublic/CSVData.py
appPublic/Config.py
appPublic/ExecFile.py
appPublic/FiniteStateMachine.py
appPublic/MiniI18N.py
appPublic/ObjectCache.py
appPublic/RSAutils.py
appPublic/SQLite3Utils.py
appPublic/Singleton.py
appPublic/__init__.py
appPublic/across_nat.bak.py
appPublic/across_nat.py
appPublic/aes.py
appPublic/app_logger.py
appPublic/argsConvert.py
appPublic/asynciorun.py
appPublic/audioplayer.py
appPublic/background.py
appPublic/base64_to_file.py
appPublic/country_cn_en.py
appPublic/csv_Data.py
appPublic/dataencoder.py
appPublic/datamapping.py
appPublic/dictExt.py
appPublic/dictObject.old.py
appPublic/dictObject.py
appPublic/easyExcel.py
appPublic/eventproperty.py
appPublic/exceldata.py
appPublic/excelwriter.py
appPublic/find_player.py
appPublic/folderUtils.py
appPublic/genetic.py
appPublic/hf.py
appPublic/http_client.py
appPublic/httpclient.py
appPublic/i18n.py
appPublic/ipgetter.py
appPublic/iplocation.py
appPublic/jsonConfig.py
appPublic/jsonIO.py
appPublic/localefunc.py
appPublic/log.py
appPublic/macAddress.py
appPublic/myImport.py
appPublic/myTE.py
appPublic/myjson.py
appPublic/mylog.py
appPublic/oauth_client.py
appPublic/objectAction.py
appPublic/outip.py
appPublic/pickleUtils.py
appPublic/port_forward.py
appPublic/process_workers.py
appPublic/proxy.py
appPublic/psm.py
appPublic/rc4.py
appPublic/receiveMail.py
appPublic/registerfunction.py
appPublic/restrictedEnv.py
appPublic/rsaPeer.py
appPublic/rsa_key_rw.py
appPublic/rsawrap.py
appPublic/set_fgcolor.py
appPublic/sockPackage.py
appPublic/sshx.py
appPublic/strUtils.py
appPublic/streamhttpclient.py
appPublic/t.py
appPublic/testdict.py
appPublic/textsplit.py
appPublic/thread_workers.py
appPublic/timeUtils.py
appPublic/timecost.py
appPublic/tworkers.py
appPublic/udp_comm.py
appPublic/uni_outip.py
appPublic/unicoding.py
appPublic/uniqueID.py
appPublic/version.py
appPublic/wav.py
appPublic/wcag_checker.py
appPublic/worker.py
appPublic/zmq_reqrep.py
appPublic/zmq_topic.py
appPublic/zmqapi.py
apppublic-5.3.0.dist-info/METADATA
apppublic-5.3.0.dist-info/WHEEL
apppublic-5.3.0.dist-info/top_level.txt
apppublic-5.3.0.dist-info/RECORD
