Metadata-Version: 2.4
Name: appPublic
Version: 5.3.0
Summary: A set of base public functions or class
Author: "yu moqing"
Author-email: "yumoqing@gmail.com"
License: "MIT"
Requires-Dist: xlrd
Requires-Dist: bs4
Requires-Dist: xlwt
Requires-Dist: nanoid
Requires-Dist: psutil
Requires-Dist: ujson
Requires-Dist: numpy
Requires-Dist: rsa
Requires-Dist: brotli
Requires-Dist: aiohttp
Requires-Dist: asyncio
Requires-Dist: aiohttp
Requires-Dist: aiohttp_socks
Requires-Dist: requests
Requires-Dist: jinja2
Requires-Dist: pyzmq
Requires-Dist: cryptography
Requires-Dist: bcrypt
Requires-Dist: asyncssh
Requires-Dist: eventpy
